setup.py
ISED_learner/ISED.py
ISED_learner/__init__.py
ISED_learner/conventional_approach.py
ISED_learner/utils.py
ised-0.1.0.dist-info/METADATA
ised-0.1.0.dist-info/WHEEL
ised-0.1.0.dist-info/licenses/LICENSE.md
ised-0.1.0.dist-info/RECORD
