Metadata-Version: 2.1
Name: ISED
Version: 0.1.0
Summary: Information-based Smoothness-enhanced Embedding Dynamics Learning Model (ISED)
Project-URL: Homepage, https://github.com/LeonBai/ISED
Author-email: "WJ.B." <wjbai@atr.jp>
License: MIT
License-File: LICENSE.md
Keywords: embedding,neural networks,spatio-temporal,time-series
Classifier: Development Status :: 4 - Beta
Classifier: Intended Audience :: Science/Research
Classifier: License :: OSI Approved :: MIT License
Classifier: Programming Language :: Python :: 3
Classifier: Programming Language :: Python :: 3.7
Classifier: Programming Language :: Python :: 3.8
Classifier: Programming Language :: Python :: 3.9
Classifier: Topic :: Scientific/Engineering :: Artificial Intelligence
Requires-Python: >=3.7
